questnav/__init__.py
questnav/commands_pb2.py
questnav/data_pb2.py
questnav/geometry2d_pb2.py
questnav/geometry3d_pb2.py
robotpy_questnav-1.1.3.dist-info/METADATA
robotpy_questnav-1.1.3.dist-info/WHEEL
robotpy_questnav-1.1.3.dist-info/top_level.txt
robotpy_questnav-1.1.3.dist-info/RECORD
