Metadata-Version: 2.4
Name: robotpy-questnav
Version: 1.1.3
Summary: QuestNav Library for Robotpy, works with pyhton now
Home-page: https://github.com/Ultime5528/FRC2025
Author: Hayder Chammakhi
Classifier: Programming Language :: Python :: 3
Classifier: License :: OSI Approved :: MIT License
Dynamic: author
Dynamic: classifier
Dynamic: home-page
Dynamic: summary
